setup.py
lavapayments.egg-info/PKG-INFO
lavapayments.egg-info/SOURCES.txt
lavapayments.egg-info/dependency_links.txt
lavapayments.egg-info/not-zip-safe
lavapayments.egg-info/top_level.txt
lavapayments/client/__init__.py
lavapayments/client/async_client.py
lavapayments/exceptions/__init__.py
lavapayments/exceptions/exceptions.py
lavapayments/types/__init__.py
lavapayments/types/bill.py
lavapayments/types/date.py
lavapayments/types/service.py