Metadata-Version: 2.1
Name: lavapayments
Version: 1.0.4
Summary: Библиотека для работы с Бизнес API Lava.ru
Author-email: dimabykov189@gmail.com
Requires: aiohttp
Requires-Python: >=3.8
